rinoh_typeface_texgyreadventor/GUST-FONT-LICENSE.txt
rinoh_typeface_texgyreadventor/README-TeX-Gyre-Adventor.txt
rinoh_typeface_texgyreadventor/__init__.py
rinoh_typeface_texgyreadventor/texgyreadventor-bold.otf
rinoh_typeface_texgyreadventor/texgyreadventor-bolditalic.otf
rinoh_typeface_texgyreadventor/texgyreadventor-italic.otf
rinoh_typeface_texgyreadventor/texgyreadventor-regular.otf
rinoh_typeface_texgyreadventor-0.1.1.dist-info/DESCRIPTION.rst
rinoh_typeface_texgyreadventor-0.1.1.dist-info/METADATA
rinoh_typeface_texgyreadventor-0.1.1.dist-info/RECORD
rinoh_typeface_texgyreadventor-0.1.1.dist-info/WHEEL
rinoh_typeface_texgyreadventor-0.1.1.dist-info/entry_points.txt
rinoh_typeface_texgyreadventor-0.1.1.dist-info/metadata.json
rinoh_typeface_texgyreadventor-0.1.1.dist-info/top_level.txt
